jlab_homepage/__init__.py
jlab_homepage/_version.py
jlab_homepage/handlers.py
jlab_homepage/tests/__init__.py
jlab_homepage/tests/test_handlers.py
jlab_homepage-0.1.13.data/data/etc/jupyter/jupyter_server_config.d/jlab_homepage.json
jlab_homepage-0.1.13.data/data/share/jupyter/labextensions/jlab_homepage/package.json
jlab_homepage-0.1.13.data/data/share/jupyter/labextensions/jlab_homepage/static/689.72d46cead16b4836f588.js
jlab_homepage-0.1.13.data/data/share/jupyter/labextensions/jlab_homepage/static/728.5104f4f0a064c3478043.js
jlab_homepage-0.1.13.data/data/share/jupyter/labextensions/jlab_homepage/static/remoteEntry.3dcfa7356c72d436c3fb.js
jlab_homepage-0.1.13.data/data/share/jupyter/labextensions/jlab_homepage/static/style.js
jlab_homepage-0.1.13.data/data/share/jupyter/labextensions/jlab_homepage/static/third-party-licenses.json
jlab_homepage-0.1.13.data/data/share/jupyter/labextensions/jlab_homepage/install.json
jlab_homepage-0.1.13.dist-info/METADATA
jlab_homepage-0.1.13.dist-info/WHEEL
jlab_homepage-0.1.13.dist-info/licenses/LICENSE
jlab_homepage-0.1.13.dist-info/RECORD
